eagleSqlTools/VERSION
eagleSqlTools/__init__.py
eagleSqlTools/_eagleSqlTools.py
eagleSqlTools/_version.py
eagleSqlTools-2.0.0.dist-info/LICENSE.md
eagleSqlTools-2.0.0.dist-info/METADATA
eagleSqlTools-2.0.0.dist-info/WHEEL
eagleSqlTools-2.0.0.dist-info/top_level.txt
eagleSqlTools-2.0.0.dist-info/RECORD
