Metadata-Version: 2.1
Name: eagleSqlTools
Version: 2.0.0
Summary: Utilities for accessing EAGLE public database.
Home-page: UNKNOWN
Author: Kyle Oman
Author-email: koman@astro.rug.nl
License: GNU GPL v3
Platform: UNKNOWN
Requires-Dist: numpy
